LICENSE
MANIFEST.in
README.rst
setup.py
reshade/__init__.py
reshade/_version.py
reshade/connection.py
reshade/fully_connected.py
reshade/neuron.py
reshade.egg-info/PKG-INFO
reshade.egg-info/SOURCES.txt
reshade.egg-info/dependency_links.txt
reshade.egg-info/not-zip-safe
reshade.egg-info/top_level.txt
reshade/ActivationFunction/__init__.py
reshade/ActivationFunction/binary_step.py
reshade/ActivationFunction/identity.py
reshade/ActivationFunction/leaky_relu.py
reshade/ActivationFunction/relu.py
reshade/ActivationFunction/sigmoid.py
reshade/ActivationFunction/tanh.py